sigmaRel_computer/ResModel.py
sigmaRel_computer/__init__.py
sigmaRel_computer/load_data.py
sigmaRel_computer/model_loader_script.py
sigmaRel_computer/plotting_script.py
sigmaRel_computer/sbc_plot_functions.py
sigmaRel_computer/sigmaRel.py
sigmaRel_computer/simulate_distances.py
sigmaRel_computer/stan_files/CombineIndividualDistances_dMCommon.stan
sigmaRel_computer/stan_files/CombineIndividualDistances_dMMixed.stan
sigmaRel_computer/stan_files/CombineIndividualDistances_dMUncorrelated.stan
sigmaRel_computer/stan_files/MultiGalFiles/sigmaRel_nomuext.stan
sigmaRel_computer/stan_files/MultiGalFiles/sigmaRel_withmuext.stan
sigmaRel_computer/stan_files/MultiGalFiles/sigmaRel_withmuext_alt.stan
sigmaRel_computer/stan_files/MultiGalFiles/sigmaRel_withmuext_alt_zmarg.stan
sigmaRel_computer/stan_files/MultiGalFiles/sigmaRel_withmuext_zmarg.stan
sigmaRel_computer/stan_files/MultiGalFiles/altpriors/sigmaRel_withmuext_altA.stan
sigmaRel_computer/stan_files/MultiGalFiles/altpriors/sigmaRel_withmuext_altB.stan
sigmaRel_computer/stan_files/MultiGalFiles/altpriors/sigmaRel_withmuext_altC.stan
sigmaRel_computer/stan_files/MultiGalFiles/altpriors/sigmaRel_withmuext_altP.stan
sigmaRel_computer/stan_files/linear_reg/linear_regression.stan
sigmaRel_computer/stan_files/linear_reg/linear_regression_fixedB.stan
sigmaRel_computer-0.0.3.dist-info/LICENSE
sigmaRel_computer-0.0.3.dist-info/METADATA
sigmaRel_computer-0.0.3.dist-info/WHEEL
sigmaRel_computer-0.0.3.dist-info/top_level.txt
sigmaRel_computer-0.0.3.dist-info/RECORD
