Metadata-Version: 2.1
Name: sigmaRel_computer
Version: 0.0.3
Summary: Package for hierarchical siblings analyses.
Author-email: "Sam M. Ward" <smward1@hotmail.com>
Project-URL: Homepage, https://github.com/sam-m-ward/sigmaRel_computer
Classifier: Programming Language :: Python :: 3
Classifier: License :: OSI Approved :: MIT License
Classifier: Operating System :: OS Independent
Requires-Python: >=3.11.5
License-File: LICENSE
